{
  "customizations": {
    "vscode": {
      "extensions": [
        "esbenp.prettier-vscode",
        "golang.go",
        "rohit-gohri.format-code-action"
      ],
      "settings": {
        "[go]": {
          "editor.defaultFormatter": "golang.go"
        },
        "editor.codeActionsOnSave": [
          "source.organizeImports",
          "source.formatDocument"
        ],
        "editor.defaultFormatter": "esbenp.prettier-vscode"
      }
    }
  },
  "image": "golang:1.25.5-alpine",
  "postCreateCommand": ".devcontainer/post-create.sh",
  "remoteEnv": {}
}
